kseniaWebsocketUtil/__init__.py
kseniaWebsocketUtil/crc.py
kseniaWebsocketUtil/websocketmanager.py
kseniaWebsocketUtil/wscall.py
kseniaWebsocketUtil-0.0.4.dist-info/LICENSE
kseniaWebsocketUtil-0.0.4.dist-info/METADATA
kseniaWebsocketUtil-0.0.4.dist-info/WHEEL
kseniaWebsocketUtil-0.0.4.dist-info/top_level.txt
kseniaWebsocketUtil-0.0.4.dist-info/RECORD
