Metadata-Version: 2.1
Name: kseniaWebsocketUtil
Version: 0.0.4
Summary: a simple websocket utility to communicate with lares units
Home-page: https://github.com/realnot16/kseniaWebsocketUtil
Author: realnot16
Author-email: benedetto.padula@gmail.com
Classifier: Development Status :: 3 - Alpha
Classifier: Intended Audience :: Developers
Classifier: Topic :: Software Development :: Libraries :: Python Modules
Classifier: Programming Language :: Python :: 3
Classifier: Programming Language :: Python :: 3.6
Classifier: Programming Language :: Python :: 3.7
Classifier: Programming Language :: Python :: 3.8
Classifier: Programming Language :: Python :: 3.9
Classifier: License :: OSI Approved :: MIT License
Classifier: Operating System :: OS Independent
Requires-Python: >=3.6
License-File: LICENSE
Requires-Dist: websockets>=10.0
